{
  "GiornoAC": "martedì 16 settembre 2025",
  "DichiarantiAC": "42",
  "ConiugiAC": "4",
  "TotaleAC": "46",
  "Euro730AC": "1.607,49 €",
  "EuroPrecompAC": "142,62 €",
  "EuroIMUAC": "24,59 €",
  "EuroAltroAC": "131,17 €",
  "EuroTotaleAC": "1.905,87 €",
  "GiornoAP": "Differenza con martedì 17 settembre 2024",
  "DichiarantiAP": "-106",
  "ConiugiAP": "-7",
  "TotaleAP": "-113",
  "Euro730AP": "-3.378,09 €",
  "EuroPrecompAP": "-373,75 €",
  "EuroIMUAP": "-56,55 €",
  "EuroAltroAP": "127,07 €",
  "EuroTotaleAP": "-3.681,32 €",
  "DichiarantiTOT": "52.587",
  "ConiugiTOT": "9.424",
  "TotaleTOT": "62.011",
  "Euro730TOT": "1.935.074,31 €",
  "EuroPrecompTOT": "142.855,35 €",
  "EuroIMUTOT": "76.191,15 €",
  "EuroAltroTOT": "10.892,84 €",
  "EuroTotaleTOT": "2.165.013,65 €",
  "TotaleDIF": "-1.024",
  "PercentualeDIF": "-1,62%",
  "Euro730DIF": "70.893,40 €",
  "EuroPrecompDIF": "753,44 €",
  "EuroIMUDIF": "6.071,42 €",
  "EuroAltroDIF": "7.804,09 €",
  "EuroTotaleDIF": "85.522,35 €",
  "AppPossibiliOggi": "238",
  "App730Oggi": "156",
  "AppLiberiOggi": "60",
  "AppBlocchiOggi": "13",
  "AppPossibiliDomani": "238",
  "App730Domani": "175",
  "AppLiberiDomani": "51",
  "AppBlocchiDomani": "15",
  "DicStessoGiornoAP": "464",
  "ConStessoGiornoAP": "-56",
  "TotStessoGiornoAP": "408",
  "DatiAggiornati": "Dati aggiornati al 16/09/2025 11:58:55"
}