{
  "GiornoAC": "martedì 10 giugno 2025",
  "DichiarantiAC": "258",
  "ConiugiAC": "58",
  "TotaleAC": "316",
  "Euro730AC": "7.620,09 €",
  "EuroPrecompAC": "854,05 €",
  "EuroIMUAC": "834,33 €",
  "EuroTotaleAC": "9.332,24 €",
  "GiornoAP": "Differenza con martedì 11 giugno 2024",
  "DichiarantiAP": "-500",
  "ConiugiAP": "-104",
  "TotaleAP": "-604",
  "Euro730AP": "-19.688,85 €",
  "EuroPrecompAP": "-1.194,92 €",
  "EuroIMUAP": "-778,55 €",
  "EuroTotaleAP": "-21.663,15 €",
  "DichiarantiTOT": "29.381",
  "ConiugiTOT": "5.567",
  "TotaleTOT": "34.948",
  "Euro730TOT": "1.085.138,69 €",
  "EuroPrecompTOT": "57.985,57 €",
  "EuroIMUTOT": "56.217,42 €",
  "EuroTotaleTOT": "1.203.403,89 €",
  "TotaleDIF": "-28.087",
  "PercentualeDIF": "-44,56%",
  "Euro730DIF": "-779.042,22 €",
  "EuroPrecompDIF": "-84.116,34 €",
  "EuroIMUDIF": "-13.902,31 €",
  "EuroTotaleDIF": "-876.087,41 €",
  "AppPossibiliOggi": "1.377",
  "App730Oggi": "1.016",
  "AppLiberiOggi": "61",
  "AppBlocchiOggi": "68",
  "AppPossibiliDomani": "1.382",
  "App730Domani": "1.039",
  "AppLiberiDomani": "48",
  "AppBlocchiDomani": "74",
  "DicStessoGiornoAP": "-136",
  "ConStessoGiornoAP": "-117",
  "TotStessoGiornoAP": "-253",
  "DatiAggiornati": "Dati aggiornati al 10/06/2025 11:46:26"
}