{
  "GiornoAC": "giovedì 9 aprile 2026",
  "DichiarantiAC": "221",
  "ConiugiAC": "31",
  "TotaleAC": "252",
  "Euro730AC": "7.179,47 €",
  "EuroPrecompAC": "234,43 €",
  "EuroIMUAC": "372,93 €",
  "EuroAltroAC": "14,75 €",
  "EuroTotaleAC": "7.801,58 €",
  "GiornoAP": "Differenza con giovedì 10 aprile 2025",
  "DichiarantiAP": "-283",
  "ConiugiAP": "-42",
  "TotaleAP": "-325",
  "Euro730AP": "-8.547,65 €",
  "EuroPrecompAP": "-241,78 €",
  "EuroIMUAP": "-161,45 €",
  "EuroAltroAP": "-15,59 €",
  "EuroTotaleAP": "-8.966,47 €",
  "DichiarantiTOT": "268",
  "ConiugiTOT": "36",
  "TotaleTOT": "304",
  "Euro730TOT": "8.243,39 €",
  "EuroPrecompTOT": "291,81 €",
  "EuroIMUTOT": "1.200,76 €",
  "EuroAltroTOT": "129,51 €",
  "EuroTotaleTOT": "9.865,47 €",
  "TotaleDIF": "-63.250",
  "PercentualeDIF": "-99,52%",
  "Euro730DIF": "-1.977.286,57 €",
  "EuroPrecompDIF": "-149.093,46 €",
  "EuroIMUDIF": "-74.616,69 €",
  "EuroAltroDIF": "-11.692,21 €",
  "EuroTotaleDIF": "-2.212.688,93 €",
  "AppPossibiliOggi": "1.112",
  "App730Oggi": "554",
  "AppLiberiOggi": "75",
  "AppBlocchiOggi": "398",
  "AppPossibiliDomani": "1.077",
  "App730Domani": "629",
  "AppLiberiDomani": "57",
  "AppBlocchiDomani": "362",
  "DicStessoGiornoAP": "-751",
  "ConStessoGiornoAP": "-127",
  "TotStessoGiornoAP": "-878",
  "DatiAggiornati": "Dati aggiornati al 09/04/2026 15:13:53"
}