{
  "GiornoAC": "martedì 28 aprile 2026",
  "DichiarantiAC": "266",
  "ConiugiAC": "54",
  "TotaleAC": "320",
  "Euro730AC": "9.577,76 €",
  "EuroPrecompAC": "559,83 €",
  "EuroIMUAC": "381,13 €",
  "EuroAltroAC": "12,30 €",
  "EuroTotaleAC": "10.531,02 €",
  "GiornoAP": "Differenza con martedì 29 aprile 2025",
  "DichiarantiAP": "-468",
  "ConiugiAP": "-67",
  "TotaleAP": "-535",
  "Euro730AP": "-16.471,32 €",
  "EuroPrecompAP": "-690,12 €",
  "EuroIMUAP": "-738,42 €",
  "EuroAltroAP": "-72,14 €",
  "EuroTotaleAP": "-17.972,00 €",
  "DichiarantiTOT": "8.427",
  "ConiugiTOT": "1.607",
  "TotaleTOT": "10.034",
  "Euro730TOT": "335.023,27 €",
  "EuroPrecompTOT": "11.214,73 €",
  "EuroIMUTOT": "13.724,90 €",
  "EuroAltroTOT": "745,13 €",
  "EuroTotaleTOT": "360.708,03 €",
  "TotaleDIF": "-53.520",
  "PercentualeDIF": "-84,21%",
  "Euro730DIF": "-1.650.506,69 €",
  "EuroPrecompDIF": "-138.170,54 €",
  "EuroIMUDIF": "-62.092,55 €",
  "EuroAltroDIF": "-11.076,59 €",
  "EuroTotaleDIF": "-1.861.846,37 €",
  "AppPossibiliOggi": "1.133",
  "App730Oggi": "932",
  "AppLiberiOggi": "54",
  "AppBlocchiOggi": "18",
  "AppPossibiliDomani": "1.128",
  "App730Domani": "979",
  "AppLiberiDomani": "32",
  "AppBlocchiDomani": "21",
  "DicStessoGiornoAP": "-165",
  "ConStessoGiornoAP": "82",
  "TotStessoGiornoAP": "-83",
  "DatiAggiornati": "Dati aggiornati al 28/04/2026 12:26:45"
}