{
  "GiornoAC": "martedì 20 maggio 2025",
  "DichiarantiAC": "334",
  "ConiugiAC": "57",
  "TotaleAC": "391",
  "Euro730AC": "10.795,68 €",
  "EuroPrecompAC": "624,60 €",
  "EuroIMUAC": "976,96 €",
  "EuroTotaleAC": "12.397,24 €",
  "GiornoAP": "Differenza con martedì 21 maggio 2024",
  "DichiarantiAP": "-13",
  "ConiugiAP": "-12",
  "TotaleAP": "-25",
  "Euro730AP": "394,35 €",
  "EuroPrecompAP": "-154,02 €",
  "EuroIMUAP": "260,67 €",
  "EuroTotaleAP": "501,00 €",
  "DichiarantiTOT": "18.930",
  "ConiugiTOT": "3.425",
  "TotaleTOT": "22.355",
  "Euro730TOT": "689.526,85 €",
  "EuroPrecompTOT": "30.617,79 €",
  "EuroIMUTOT": "33.245,76 €",
  "EuroTotaleTOT": "755.992,46 €",
  "TotaleDIF": "-40.680",
  "PercentualeDIF": "-64,54%",
  "Euro730DIF": "-1.174.654,06 €",
  "EuroPrecompDIF": "-111.484,12 €",
  "EuroIMUDIF": "-36.873,97 €",
  "EuroTotaleDIF": "-1.323.498,84 €",
  "AppPossibiliOggi": "1.167",
  "App730Oggi": "1.016",
  "AppLiberiOggi": "33",
  "AppBlocchiOggi": "23",
  "AppPossibiliDomani": "1.169",
  "App730Domani": "1.057",
  "AppLiberiDomani": "16",
  "AppBlocchiDomani": "18",
  "DicStessoGiornoAP": "1.318",
  "ConStessoGiornoAP": "170",
  "TotStessoGiornoAP": "1.488",
  "DatiAggiornati": "Dati aggiornati al 20/05/2025 12:32:29"
}