{
  "GiornoAC": "venerdì 16 maggio 2025",
  "DichiarantiAC": "334",
  "ConiugiAC": "66",
  "TotaleAC": "400",
  "Euro730AC": "10.148,10 €",
  "EuroPrecompAC": "670,48 €",
  "EuroIMUAC": "701,56 €",
  "EuroTotaleAC": "11.539,00 €",
  "GiornoAP": "Differenza con venerdì 17 maggio 2024",
  "DichiarantiAP": "-374",
  "ConiugiAP": "-93",
  "TotaleAP": "-467",
  "Euro730AP": "-16.737,79 €",
  "EuroPrecompAP": "-649,10 €",
  "EuroIMUAP": "-1.149,83 €",
  "EuroTotaleAP": "-18.554,76 €",
  "DichiarantiTOT": "17.337",
  "ConiugiTOT": "3.129",
  "TotaleTOT": "20.466",
  "Euro730TOT": "632.157,03 €",
  "EuroPrecompTOT": "26.345,03 €",
  "EuroIMUTOT": "30.324,70 €",
  "EuroTotaleTOT": "691.148,47 €",
  "TotaleDIF": "-42.569",
  "PercentualeDIF": "-67,53%",
  "Euro730DIF": "-1.232.023,88 €",
  "EuroPrecompDIF": "-115.756,88 €",
  "EuroIMUDIF": "-39.795,03 €",
  "EuroTotaleDIF": "-1.388.342,83 €",
  "AppPossibiliOggi": "1.153",
  "App730Oggi": "1.063",
  "AppLiberiOggi": "26",
  "AppBlocchiOggi": "30",
  "AppPossibiliDomani": "0",
  "App730Domani": "0",
  "AppLiberiDomani": "0",
  "AppBlocchiDomani": "0",
  "DicStessoGiornoAP": "861",
  "ConStessoGiornoAP": "95",
  "TotStessoGiornoAP": "956",
  "DatiAggiornati": "Dati aggiornati al 16/05/2025 12:21:46"
}