{
  "GiornoAC": "martedì 10 giugno 2025",
  "DichiarantiAC": "4",
  "ConiugiAC": "1",
  "TotaleAC": "5",
  "Euro730AC": "120,50 €",
  "EuroPrecompAC": "16,39 €",
  "EuroIMUAC": "24,59 €",
  "EuroTotaleAC": "161,48 €",
  "GiornoAP": "Differenza con martedì 11 giugno 2024",
  "DichiarantiAP": "-754",
  "ConiugiAP": "-161",
  "TotaleAP": "-915",
  "Euro730AP": "-27.188,44 €",
  "EuroPrecompAP": "-2.032,58 €",
  "EuroIMUAP": "-1.588,29 €",
  "EuroTotaleAP": "-30.833,91 €",
  "DichiarantiTOT": "29.127",
  "ConiugiTOT": "5.511",
  "TotaleTOT": "34.638",
  "Euro730TOT": "1.077.639,10 €",
  "EuroPrecompTOT": "57.147,91 €",
  "EuroIMUTOT": "55.407,68 €",
  "EuroTotaleTOT": "1.194.233,13 €",
  "TotaleDIF": "-28.397",
  "PercentualeDIF": "-45,05%",
  "Euro730DIF": "-786.541,81 €",
  "EuroPrecompDIF": "-84.954,00 €",
  "EuroIMUDIF": "-14.712,05 €",
  "EuroTotaleDIF": "-885.258,17 €",
  "AppPossibiliOggi": "1.377",
  "App730Oggi": "1.032",
  "AppLiberiOggi": "40",
  "AppBlocchiOggi": "68",
  "AppPossibiliDomani": "1.382",
  "App730Domani": "1.044",
  "AppLiberiDomani": "45",
  "AppBlocchiDomani": "72",
  "DicStessoGiornoAP": "-390",
  "ConStessoGiornoAP": "-173",
  "TotStessoGiornoAP": "-563",
  "DatiAggiornati": "Dati aggiornati al 10/06/2025 09:06:25"
}