{
  "GiornoAC": "venerdì 29 maggio 2026",
  "DichiarantiAC": "45",
  "ConiugiAC": "9",
  "TotaleAC": "54",
  "Euro730AC": "1.512,32 €",
  "EuroPrecompAC": "222,95 €",
  "EuroIMUAC": "61,47 €",
  "EuroAltroAC": "0,00 €",
  "EuroTotaleAC": "1.796,74 €",
  "GiornoAP": "Differenza con venerdì 30 maggio 2025",
  "DichiarantiAP": "-730",
  "ConiugiAP": "-159",
  "TotaleAP": "-889",
  "Euro730AP": "-27.294,31 €",
  "EuroPrecompAP": "-1.905,68 €",
  "EuroIMUAP": "-1.254,80 €",
  "EuroAltroAP": "-260,70 €",
  "EuroTotaleAP": "-30.715,49 €",
  "DichiarantiTOT": "24.910",
  "ConiugiTOT": "4.674",
  "TotaleTOT": "29.584",
  "Euro730TOT": "970.861,32 €",
  "EuroPrecompTOT": "50.280,25 €",
  "EuroIMUTOT": "48.387,78 €",
  "EuroAltroTOT": "3.446,85 €",
  "EuroTotaleTOT": "1.072.976,20 €",
  "TotaleDIF": "-33.970",
  "PercentualeDIF": "-53,45%",
  "Euro730DIF": "-1.014.668,64 €",
  "EuroPrecompDIF": "-99.105,02 €",
  "EuroIMUDIF": "-27.429,67 €",
  "EuroAltroDIF": "-8.374,87 €",
  "EuroTotaleDIF": "-1.149.578,20 €",
  "AppPossibiliOggi": "1.077",
  "App730Oggi": "984",
  "AppLiberiOggi": "23",
  "AppBlocchiOggi": "10",
  "AppPossibiliDomani": "0",
  "App730Domani": "0",
  "AppLiberiDomani": "0",
  "AppBlocchiDomani": "0",
  "DicStessoGiornoAP": "-799",
  "ConStessoGiornoAP": "-173",
  "TotStessoGiornoAP": "-972",
  "DatiAggiornati": "Dati aggiornati al 29/05/2026 09:38:35"
}