{
  "GiornoAC": "mercoledì 22 aprile 2026",
  "DichiarantiAC": "697",
  "ConiugiAC": "145",
  "TotaleAC": "842",
  "Euro730AC": "29.199,43 €",
  "EuroPrecompAC": "1.353,23 €",
  "EuroIMUAC": "905,71 €",
  "EuroAltroAC": "95,90 €",
  "EuroTotaleAC": "31.554,27 €",
  "GiornoAP": "Differenza con mercoledì 23 aprile 2025",
  "DichiarantiAP": "-42",
  "ConiugiAP": "15",
  "TotaleAP": "-27",
  "Euro730AP": "1.114,09 €",
  "EuroPrecompAP": "86,06 €",
  "EuroIMUAP": "-264,67 €",
  "EuroAltroAP": "59,82 €",
  "EuroTotaleAP": "995,30 €",
  "DichiarantiTOT": "5.984",
  "ConiugiTOT": "1.162",
  "TotaleTOT": "7.146",
  "Euro730TOT": "236.816,85 €",
  "EuroPrecompTOT": "7.658,16 €",
  "EuroIMUTOT": "9.802,93 €",
  "EuroAltroTOT": "663,98 €",
  "EuroTotaleTOT": "254.941,92 €",
  "TotaleDIF": "-56.408",
  "PercentualeDIF": "-88,76%",
  "Euro730DIF": "-1.748.713,11 €",
  "EuroPrecompDIF": "-141.727,11 €",
  "EuroIMUDIF": "-66.014,52 €",
  "EuroAltroDIF": "-11.157,74 €",
  "EuroTotaleDIF": "-1.967.612,48 €",
  "AppPossibiliOggi": "1.128",
  "App730Oggi": "967",
  "AppLiberiOggi": "57",
  "AppBlocchiOggi": "25",
  "AppPossibiliDomani": "1.112",
  "App730Domani": "985",
  "AppLiberiDomani": "17",
  "AppBlocchiDomani": "4",
  "DicStessoGiornoAP": "-349",
  "ConStessoGiornoAP": "44",
  "TotStessoGiornoAP": "-305",
  "DatiAggiornati": "Dati aggiornati al 22/04/2026 19:45:52"
}