{
  "GiornoAC": "lunedì 26 maggio 2025",
  "DichiarantiAC": "777",
  "ConiugiAC": "176",
  "TotaleAC": "953",
  "Euro730AC": "28.328,79 €",
  "EuroPrecompAC": "2.212,13 €",
  "EuroIMUAC": "1.380,18 €",
  "EuroTotaleAC": "32.007,18 €",
  "GiornoAP": "Differenza con lunedì 27 maggio 2024",
  "DichiarantiAP": "-27",
  "ConiugiAP": "5",
  "TotaleAP": "-22",
  "Euro730AP": "301,85 €",
  "EuroPrecompAP": "-246,67 €",
  "EuroIMUAP": "209,85 €",
  "EuroTotaleAP": "314,21 €",
  "DichiarantiTOT": "22.437",
  "ConiugiTOT": "4.155",
  "TotaleTOT": "26.592",
  "Euro730TOT": "824.397,10 €",
  "EuroPrecompTOT": "39.683,84 €",
  "EuroIMUTOT": "40.184,45 €",
  "EuroTotaleTOT": "907.429,83 €",
  "TotaleDIF": "-36.443",
  "PercentualeDIF": "-57,81%",
  "Euro730DIF": "-1.039.783,81 €",
  "EuroPrecompDIF": "-102.418,07 €",
  "EuroIMUDIF": "-29.935,28 €",
  "EuroTotaleDIF": "-1.172.061,47 €",
  "AppPossibiliOggi": "1.162",
  "App730Oggi": "1.035",
  "AppLiberiOggi": "45",
  "AppBlocchiOggi": "27",
  "AppPossibiliDomani": "1.167",
  "App730Domani": "989",
  "AppLiberiDomani": "21",
  "AppBlocchiDomani": "45",
  "DicStessoGiornoAP": "1.550",
  "ConStessoGiornoAP": "246",
  "TotStessoGiornoAP": "1.796",
  "DatiAggiornati": "Dati aggiornati al 26/05/2025 18:59:38"
}