{
  "GiornoAC": "martedì 14 luglio 2026",
  "DichiarantiAC": "152",
  "ConiugiAC": "13",
  "TotaleAC": "165",
  "Euro730AC": "5.235,93 €",
  "EuroPrecompAC": "331,96 €",
  "EuroIMUAC": "90,16 €",
  "EuroAltroAC": "200,81 €",
  "EuroTotaleAC": "5.858,86 €",
  "GiornoAP": "Differenza con martedì 15 luglio 2025",
  "DichiarantiAP": "-406",
  "ConiugiAP": "-62",
  "TotaleAP": "-468",
  "Euro730AP": "-15.199,82 €",
  "EuroPrecompAP": "-1.851,45 €",
  "EuroIMUAP": "-103,26 €",
  "EuroAltroAP": "12,23 €",
  "EuroTotaleAP": "-17.142,30 €",
  "DichiarantiTOT": "46.708",
  "ConiugiTOT": "8.716",
  "TotaleTOT": "55.424",
  "Euro730TOT": "1.792.014,22 €",
  "EuroPrecompTOT": "121.612,53 €",
  "EuroIMUTOT": "80.653,47 €",
  "EuroAltroTOT": "10.984,74 €",
  "EuroTotaleTOT": "2.005.264,96 €",
  "TotaleDIF": "-8.130",
  "PercentualeDIF": "-12,79%",
  "Euro730DIF": "-193.515,74 €",
  "EuroPrecompDIF": "-27.772,74 €",
  "EuroIMUDIF": "4.836,02 €",
  "EuroAltroDIF": "-836,98 €",
  "EuroTotaleDIF": "-217.289,44 €",
  "AppPossibiliOggi": "1.119",
  "App730Oggi": "569",
  "AppLiberiOggi": "441",
  "AppBlocchiOggi": "27",
  "AppPossibiliDomani": "1.128",
  "App730Domani": "474",
  "AppLiberiDomani": "537",
  "AppBlocchiDomani": "41",
  "DicStessoGiornoAP": "-975",
  "ConStessoGiornoAP": "-139",
  "TotStessoGiornoAP": "-1.114",
  "DatiAggiornati": "Dati aggiornati al 14/07/2026 11:12:54"
}