{
  "GiornoAC": "martedì 1 luglio 2025",
  "DichiarantiAC": "73",
  "ConiugiAC": "12",
  "TotaleAC": "85",
  "Euro730AC": "2.499,33 €",
  "EuroPrecompAC": "336,03 €",
  "EuroIMUAC": "54,09 €",
  "EuroTotaleAC": "2.889,45 €",
  "GiornoAP": "Differenza con martedì 2 luglio 2024",
  "DichiarantiAP": "-603",
  "ConiugiAP": "-91",
  "TotaleAP": "-694",
  "Euro730AP": "-21.575,92 €",
  "EuroPrecompAP": "-1.073,67 €",
  "EuroIMUAP": "-408,96 €",
  "EuroTotaleAP": "-23.058,55 €",
  "DichiarantiTOT": "40.684",
  "ConiugiTOT": "7.774",
  "TotaleTOT": "48.458",
  "Euro730TOT": "1.498.274,77 €",
  "EuroPrecompTOT": "94.331,44 €",
  "EuroIMUTOT": "70.614,53 €",
  "EuroTotaleTOT": "1.669.177,53 €",
  "TotaleDIF": "-14.577",
  "PercentualeDIF": "-23,13%",
  "Euro730DIF": "-365.906,14 €",
  "EuroPrecompDIF": "-47.770,47 €",
  "EuroIMUDIF": "494,80 €",
  "EuroTotaleDIF": "-410.313,77 €",
  "AppPossibiliOggi": "1.377",
  "App730Oggi": "920",
  "AppLiberiOggi": "152",
  "AppBlocchiOggi": "130",
  "AppPossibiliDomani": "1.382",
  "App730Domani": "963",
  "AppLiberiDomani": "161",
  "AppBlocchiDomani": "106",
  "DicStessoGiornoAP": "214",
  "ConStessoGiornoAP": "41",
  "TotStessoGiornoAP": "255",
  "DatiAggiornati": "Dati aggiornati al 01/07/2025 09:57:13"
}