{
  "GiornoAC": "lunedì 25 maggio 2026",
  "DichiarantiAC": "406",
  "ConiugiAC": "63",
  "TotaleAC": "469",
  "Euro730AC": "14.121,09 €",
  "EuroPrecompAC": "1.004,92 €",
  "EuroIMUAC": "856,51 €",
  "EuroAltroAC": "153,26 €",
  "EuroTotaleAC": "16.135,78 €",
  "GiornoAP": "Differenza con lunedì 26 maggio 2025",
  "DichiarantiAP": "-398",
  "ConiugiAP": "-124",
  "TotaleAP": "-522",
  "Euro730AP": "-15.468,44 €",
  "EuroPrecompAP": "-1.240,81 €",
  "EuroIMUAP": "-548,26 €",
  "EuroAltroAP": "67,18 €",
  "EuroTotaleAP": "-17.190,33 €",
  "DichiarantiTOT": "22.101",
  "ConiugiTOT": "4.139",
  "TotaleTOT": "26.240",
  "Euro730TOT": "867.334,38 €",
  "EuroPrecompTOT": "41.203,27 €",
  "EuroIMUTOT": "41.752,69 €",
  "EuroAltroTOT": "2.705,84 €",
  "EuroTotaleTOT": "952.996,18 €",
  "TotaleDIF": "-37.314",
  "PercentualeDIF": "-58,71%",
  "Euro730DIF": "-1.118.195,58 €",
  "EuroPrecompDIF": "-108.182,00 €",
  "EuroIMUDIF": "-34.064,76 €",
  "EuroAltroDIF": "-9.115,88 €",
  "EuroTotaleDIF": "-1.269.558,22 €",
  "AppPossibiliOggi": "1.124",
  "App730Oggi": "1.018",
  "AppLiberiOggi": "44",
  "AppBlocchiOggi": "16",
  "AppPossibiliDomani": "1.133",
  "App730Domani": "1.032",
  "AppLiberiDomani": "16",
  "AppBlocchiDomani": "4",
  "DicStessoGiornoAP": "-538",
  "ConStessoGiornoAP": "-65",
  "TotStessoGiornoAP": "-603",
  "DatiAggiornati": "Dati aggiornati al 25/05/2026 13:57:51"
}