{
  "GiornoAC": "lunedì 26 maggio 2025",
  "DichiarantiAC": "467",
  "ConiugiAC": "114",
  "TotaleAC": "581",
  "Euro730AC": "16.886,23 €",
  "EuroPrecompAC": "1.308,92 €",
  "EuroIMUAC": "973,66 €",
  "EuroTotaleAC": "19.254,89 €",
  "GiornoAP": "Differenza con lunedì 27 maggio 2024",
  "DichiarantiAP": "-337",
  "ConiugiAP": "-57",
  "TotaleAP": "-394",
  "Euro730AP": "-11.140,71 €",
  "EuroPrecompAP": "-1.149,88 €",
  "EuroIMUAP": "-196,67 €",
  "EuroTotaleAP": "-12.438,08 €",
  "DichiarantiTOT": "22.136",
  "ConiugiTOT": "4.095",
  "TotaleTOT": "26.231",
  "Euro730TOT": "812.954,54 €",
  "EuroPrecompTOT": "38.780,63 €",
  "EuroIMUTOT": "39.777,93 €",
  "EuroTotaleTOT": "894.677,54 €",
  "TotaleDIF": "-36.804",
  "PercentualeDIF": "-58,39%",
  "Euro730DIF": "-1.051.226,37 €",
  "EuroPrecompDIF": "-103.321,28 €",
  "EuroIMUDIF": "-30.341,80 €",
  "EuroTotaleDIF": "-1.184.813,76 €",
  "AppPossibiliOggi": "1.162",
  "App730Oggi": "1.037",
  "AppLiberiOggi": "43",
  "AppBlocchiOggi": "27",
  "AppPossibiliDomani": "1.167",
  "App730Domani": "994",
  "AppLiberiDomani": "15",
  "AppBlocchiDomani": "45",
  "DicStessoGiornoAP": "1.249",
  "ConStessoGiornoAP": "186",
  "TotStessoGiornoAP": "1.435",
  "DatiAggiornati": "Dati aggiornati al 26/05/2025 15:44:39"
}