{
  "GiornoAC": "lunedì 4 agosto 2025",
  "DichiarantiAC": "46",
  "ConiugiAC": "6",
  "TotaleAC": "52",
  "Euro730AC": "1.501,74 €",
  "EuroPrecompAC": "587,64 €",
  "EuroIMUAC": "24,59 €",
  "EuroTotaleAC": "2.113,97 €",
  "GiornoAP": "Differenza con lunedì 5 agosto 2024",
  "DichiarantiAP": "-38",
  "ConiugiAP": "-7",
  "TotaleAP": "-45",
  "Euro730AP": "-869,73 €",
  "EuroPrecompAP": "136,85 €",
  "EuroIMUAP": "-31,14 €",
  "EuroTotaleAP": "-772,22 €",
  "DichiarantiTOT": "50.341",
  "ConiugiTOT": "9.210",
  "TotaleTOT": "59.551",
  "Euro730TOT": "1.852.277,22 €",
  "EuroPrecompTOT": "132.686,26 €",
  "EuroIMUTOT": "74.987,97 €",
  "EuroTotaleTOT": "2.068.853,06 €",
  "TotaleDIF": "-3.484",
  "PercentualeDIF": "-5,53%",
  "Euro730DIF": "-11.903,69 €",
  "EuroPrecompDIF": "-9.415,65 €",
  "EuroIMUDIF": "4.868,24 €",
  "EuroTotaleDIF": "-10.638,24 €",
  "AppPossibiliOggi": "399",
  "App730Oggi": "137",
  "AppLiberiOggi": "44",
  "AppBlocchiOggi": "164",
  "AppPossibiliDomani": "392",
  "App730Domani": "150",
  "AppLiberiDomani": "29",
  "AppBlocchiDomani": "124",
  "DicStessoGiornoAP": "185",
  "ConStessoGiornoAP": "-57",
  "TotStessoGiornoAP": "128",
  "DatiAggiornati": "Dati aggiornati al 04/08/2025 12:55:55"
}