{
  "GiornoAC": "martedì 19 maggio 2026",
  "DichiarantiAC": "191",
  "ConiugiAC": "40",
  "TotaleAC": "231",
  "Euro730AC": "6.701,55 €",
  "EuroPrecompAC": "435,26 €",
  "EuroIMUAC": "348,35 €",
  "EuroAltroAC": "47,54 €",
  "EuroTotaleAC": "7.532,70 €",
  "GiornoAP": "Differenza con martedì 20 maggio 2025",
  "DichiarantiAP": "-596",
  "ConiugiAP": "-105",
  "TotaleAP": "-701",
  "Euro730AP": "-21.476,30 €",
  "EuroPrecompAP": "-1.642,59 €",
  "EuroIMUAP": "-1.708,84 €",
  "EuroAltroAP": "35,24 €",
  "EuroTotaleAP": "-24.792,49 €",
  "DichiarantiTOT": "18.824",
  "ConiugiTOT": "3.498",
  "TotaleTOT": "22.322",
  "Euro730TOT": "737.627,36 €",
  "EuroPrecompTOT": "32.407,38 €",
  "EuroIMUTOT": "34.433,25 €",
  "EuroAltroTOT": "1.864,04 €",
  "EuroTotaleTOT": "806.332,03 €",
  "TotaleDIF": "-41.232",
  "PercentualeDIF": "-64,88%",
  "Euro730DIF": "-1.247.902,60 €",
  "EuroPrecompDIF": "-116.977,89 €",
  "EuroIMUDIF": "-41.384,20 €",
  "EuroAltroDIF": "-9.957,68 €",
  "EuroTotaleDIF": "-1.416.222,37 €",
  "AppPossibiliOggi": "1.133",
  "App730Oggi": "999",
  "AppLiberiOggi": "23",
  "AppBlocchiOggi": "31",
  "AppPossibiliDomani": "1.128",
  "App730Domani": "1.047",
  "AppLiberiDomani": "10",
  "AppBlocchiDomani": "16",
  "DicStessoGiornoAP": "-669",
  "ConStessoGiornoAP": "-41",
  "TotStessoGiornoAP": "-710",
  "DatiAggiornati": "Dati aggiornati al 19/05/2026 10:56:58"
}