{
  "GiornoAC": "mercoledì 6 agosto 2025",
  "DichiarantiAC": "113",
  "ConiugiAC": "15",
  "TotaleAC": "128",
  "Euro730AC": "3.503,47 €",
  "EuroPrecompAC": "1.089,21 €",
  "EuroIMUAC": "122,95 €",
  "EuroTotaleAC": "4.732,03 €",
  "GiornoAP": "Differenza con mercoledì 7 agosto 2024",
  "DichiarantiAP": "16",
  "ConiugiAP": "-4",
  "TotaleAP": "12",
  "Euro730AP": "-604,17 €",
  "EuroPrecompAP": "736,76 €",
  "EuroIMUAP": "80,33 €",
  "EuroTotaleAP": "155,52 €",
  "DichiarantiTOT": "50.623",
  "ConiugiTOT": "9.244",
  "TotaleTOT": "59.867",
  "Euro730TOT": "1.861.415,47 €",
  "EuroPrecompTOT": "134.569,69 €",
  "EuroIMUTOT": "75.281,40 €",
  "EuroTotaleTOT": "2.080.340,34 €",
  "TotaleDIF": "-3.168",
  "PercentualeDIF": "-5,03%",
  "Euro730DIF": "-2.765,44 €",
  "EuroPrecompDIF": "-7.532,22 €",
  "EuroIMUDIF": "5.161,67 €",
  "EuroTotaleDIF": "849,04 €",
  "AppPossibiliOggi": "388",
  "App730Oggi": "143",
  "AppLiberiOggi": "39",
  "AppBlocchiOggi": "125",
  "AppPossibiliDomani": "430",
  "App730Domani": "151",
  "AppLiberiDomani": "33",
  "AppBlocchiDomani": "200",
  "DicStessoGiornoAP": "253",
  "ConStessoGiornoAP": "-60",
  "TotStessoGiornoAP": "193",
  "DatiAggiornati": "Dati aggiornati al 06/08/2025 17:46:09"
}