{
  "GiornoAC": "martedì 24 giugno 2025",
  "DichiarantiAC": "57",
  "ConiugiAC": "8",
  "TotaleAC": "65",
  "Euro730AC": "1.957,50 €",
  "EuroPrecompAC": "105,74 €",
  "EuroIMUAC": "85,24 €",
  "EuroTotaleAC": "2.148,48 €",
  "GiornoAP": "Differenza con martedì 25 giugno 2024",
  "DichiarantiAP": "-717",
  "ConiugiAP": "-168",
  "TotaleAP": "-885",
  "Euro730AP": "-25.110,48 €",
  "EuroPrecompAP": "-2.303,86 €",
  "EuroIMUAP": "-618,75 €",
  "EuroTotaleAP": "-28.033,09 €",
  "DichiarantiTOT": "36.973",
  "ConiugiTOT": "7.049",
  "TotaleTOT": "44.022",
  "Euro730TOT": "1.360.497,42 €",
  "EuroPrecompTOT": "81.389,71 €",
  "EuroIMUTOT": "67.398,39 €",
  "EuroTotaleTOT": "1.514.585,65 €",
  "TotaleDIF": "-19.013",
  "PercentualeDIF": "-30,16%",
  "Euro730DIF": "-503.683,49 €",
  "EuroPrecompDIF": "-60.712,20 €",
  "EuroIMUDIF": "-2.721,34 €",
  "EuroTotaleDIF": "-564.905,65 €",
  "AppPossibiliOggi": "1.377",
  "App730Oggi": "979",
  "AppLiberiOggi": "72",
  "AppBlocchiOggi": "85",
  "AppPossibiliDomani": "1.382",
  "App730Domani": "1.008",
  "AppLiberiDomani": "77",
  "AppBlocchiDomani": "92",
  "DicStessoGiornoAP": "136",
  "ConStessoGiornoAP": "-26",
  "TotStessoGiornoAP": "110",
  "DatiAggiornati": "Dati aggiornati al 24/06/2025 09:42:01"
}