{
  "GiornoAC": "mercoledì 29 aprile 2026",
  "DichiarantiAC": "206",
  "ConiugiAC": "38",
  "TotaleAC": "244",
  "Euro730AC": "8.259,67 €",
  "EuroPrecompAC": "168,85 €",
  "EuroIMUAC": "299,17 €",
  "EuroAltroAC": "53,28 €",
  "EuroTotaleAC": "8.780,97 €",
  "GiornoAP": "Differenza con mercoledì 30 aprile 2025",
  "DichiarantiAP": "-532",
  "ConiugiAP": "-82",
  "TotaleAP": "-614",
  "Euro730AP": "-20.016,65 €",
  "EuroPrecompAP": "-1.259,76 €",
  "EuroIMUAP": "-1.025,27 €",
  "EuroAltroAP": "-95,91 €",
  "EuroTotaleAP": "-22.397,59 €",
  "DichiarantiTOT": "9.053",
  "ConiugiTOT": "1.703",
  "TotaleTOT": "10.756",
  "Euro730TOT": "359.880,12 €",
  "EuroPrecompTOT": "12.122,09 €",
  "EuroIMUTOT": "14.458,47 €",
  "EuroAltroTOT": "851,69 €",
  "EuroTotaleTOT": "387.312,37 €",
  "TotaleDIF": "-52.798",
  "PercentualeDIF": "-83,08%",
  "Euro730DIF": "-1.625.649,84 €",
  "EuroPrecompDIF": "-137.263,18 €",
  "EuroIMUDIF": "-61.358,98 €",
  "EuroAltroDIF": "-10.970,03 €",
  "EuroTotaleDIF": "-1.835.242,03 €",
  "AppPossibiliOggi": "1.128",
  "App730Oggi": "966",
  "AppLiberiOggi": "45",
  "AppBlocchiOggi": "23",
  "AppPossibiliDomani": "1.112",
  "App730Domani": "952",
  "AppLiberiDomani": "38",
  "AppBlocchiDomani": "5",
  "DicStessoGiornoAP": "-275",
  "ConStessoGiornoAP": "58",
  "TotStessoGiornoAP": "-217",
  "DatiAggiornati": "Dati aggiornati al 29/04/2026 11:38:04"
}