{
  "GiornoAC": "venerdì 29 maggio 2026",
  "DichiarantiAC": "85",
  "ConiugiAC": "18",
  "TotaleAC": "103",
  "Euro730AC": "2.956,56 €",
  "EuroPrecompAC": "298,36 €",
  "EuroIMUAC": "102,45 €",
  "EuroAltroAC": "0,00 €",
  "EuroTotaleAC": "3.357,37 €",
  "GiornoAP": "Differenza con venerdì 30 maggio 2025",
  "DichiarantiAP": "-690",
  "ConiugiAP": "-150",
  "TotaleAP": "-840",
  "Euro730AP": "-25.850,07 €",
  "EuroPrecompAP": "-1.830,27 €",
  "EuroIMUAP": "-1.213,82 €",
  "EuroAltroAP": "-260,70 €",
  "EuroTotaleAP": "-29.154,86 €",
  "DichiarantiTOT": "24.951",
  "ConiugiTOT": "4.683",
  "TotaleTOT": "29.634",
  "Euro730TOT": "972.305,56 €",
  "EuroPrecompTOT": "50.355,66 €",
  "EuroIMUTOT": "48.428,76 €",
  "EuroAltroTOT": "3.446,85 €",
  "EuroTotaleTOT": "1.074.536,83 €",
  "TotaleDIF": "-33.920",
  "PercentualeDIF": "-53,37%",
  "Euro730DIF": "-1.013.224,40 €",
  "EuroPrecompDIF": "-99.029,61 €",
  "EuroIMUDIF": "-27.388,69 €",
  "EuroAltroDIF": "-8.374,87 €",
  "EuroTotaleDIF": "-1.148.017,57 €",
  "AppPossibiliOggi": "1.077",
  "App730Oggi": "983",
  "AppLiberiOggi": "23",
  "AppBlocchiOggi": "11",
  "AppPossibiliDomani": "0",
  "App730Domani": "0",
  "AppLiberiDomani": "0",
  "AppBlocchiDomani": "0",
  "DicStessoGiornoAP": "-758",
  "ConStessoGiornoAP": "-164",
  "TotStessoGiornoAP": "-922",
  "DatiAggiornati": "Dati aggiornati al 29/05/2026 10:08:35"
}