{
  "GiornoAC": "lunedì 30 giugno 2025",
  "DichiarantiAC": "286",
  "ConiugiAC": "61",
  "TotaleAC": "347",
  "Euro730AC": "9.653,02 €",
  "EuroPrecompAC": "1.321,18 €",
  "EuroIMUAC": "236,04 €",
  "EuroTotaleAC": "11.222,54 €",
  "GiornoAP": "Differenza con lunedì 1 luglio 2024",
  "DichiarantiAP": "-393",
  "ConiugiAP": "-60",
  "TotaleAP": "-453",
  "Euro730AP": "-14.854,20 €",
  "EuroPrecompAP": "-1.817,75 €",
  "EuroIMUAP": "22,13 €",
  "EuroTotaleAP": "-16.637,52 €",
  "DichiarantiTOT": "40.128",
  "ConiugiTOT": "7.660",
  "TotaleTOT": "47.788",
  "Euro730TOT": "1.477.282,44 €",
  "EuroPrecompTOT": "92.476,62 €",
  "EuroIMUTOT": "70.165,39 €",
  "EuroTotaleTOT": "1.645.827,96 €",
  "TotaleDIF": "-15.247",
  "PercentualeDIF": "-24,19%",
  "Euro730DIF": "-386.898,47 €",
  "EuroPrecompDIF": "-49.625,29 €",
  "EuroIMUDIF": "45,66 €",
  "EuroTotaleDIF": "-433.663,34 €",
  "AppPossibiliOggi": "1.386",
  "App730Oggi": "929",
  "AppLiberiOggi": "97",
  "AppBlocchiOggi": "264",
  "AppPossibiliDomani": "1.377",
  "App730Domani": "940",
  "AppLiberiDomani": "134",
  "AppBlocchiDomani": "125",
  "DicStessoGiornoAP": "334",
  "ConStessoGiornoAP": "30",
  "TotStessoGiornoAP": "364",
  "DatiAggiornati": "Dati aggiornati al 30/06/2025 12:17:12"
}