{
  "GiornoAC": "giovedì 16 luglio 2026",
  "DichiarantiAC": "183",
  "ConiugiAC": "24",
  "TotaleAC": "207",
  "Euro730AC": "5.489,21 €",
  "EuroPrecompAC": "1.966,20 €",
  "EuroIMUAC": "180,33 €",
  "EuroAltroAC": "29,50 €",
  "EuroTotaleAC": "7.665,24 €",
  "GiornoAP": "Differenza con giovedì 17 luglio 2025",
  "DichiarantiAP": "-263",
  "ConiugiAP": "-37",
  "TotaleAP": "-300",
  "Euro730AP": "-10.465,06 €",
  "EuroPrecompAP": "275,37 €",
  "EuroIMUAP": "-19,65 €",
  "EuroAltroAP": "-38,56 €",
  "EuroTotaleAP": "-10.247,90 €",
  "DichiarantiTOT": "47.662",
  "ConiugiTOT": "8.847",
  "TotaleTOT": "56.509",
  "Euro730TOT": "1.826.460,70 €",
  "EuroPrecompTOT": "125.796,71 €",
  "EuroIMUTOT": "81.313,31 €",
  "EuroAltroTOT": "11.310,14 €",
  "EuroTotaleTOT": "2.044.880,86 €",
  "TotaleDIF": "-7.045",
  "PercentualeDIF": "-11,09%",
  "Euro730DIF": "-159.069,26 €",
  "EuroPrecompDIF": "-23.588,56 €",
  "EuroIMUDIF": "5.495,86 €",
  "EuroAltroDIF": "-511,58 €",
  "EuroTotaleDIF": "-177.673,54 €",
  "AppPossibiliOggi": "1.112",
  "App730Oggi": "463",
  "AppLiberiOggi": "528",
  "AppBlocchiOggi": "60",
  "AppPossibiliDomani": "1.070",
  "App730Domani": "481",
  "AppLiberiDomani": "477",
  "AppBlocchiDomani": "67",
  "DicStessoGiornoAP": "-997",
  "ConStessoGiornoAP": "-155",
  "TotStessoGiornoAP": "-1.152",
  "DatiAggiornati": "Dati aggiornati al 16/07/2026 13:21:44"
}