{
  "GiornoAC": "mercoledì 9 luglio 2025",
  "DichiarantiAC": "436",
  "ConiugiAC": "70",
  "TotaleAC": "506",
  "Euro730AC": "15.771,53 €",
  "EuroPrecompAC": "1.306,46 €",
  "EuroIMUAC": "298,34 €",
  "EuroTotaleAC": "17.464,04 €",
  "GiornoAP": "Differenza con mercoledì 10 luglio 2024",
  "DichiarantiAP": "-145",
  "ConiugiAP": "-23",
  "TotaleAP": "-168",
  "Euro730AP": "-4.801,88 €",
  "EuroPrecompAP": "-816,22 €",
  "EuroIMUAP": "45,91 €",
  "EuroTotaleAP": "-5.521,38 €",
  "DichiarantiTOT": "45.145",
  "ConiugiTOT": "8.493",
  "TotaleTOT": "53.638",
  "Euro730TOT": "1.664.363,81 €",
  "EuroPrecompTOT": "109.087,72 €",
  "EuroIMUTOT": "72.737,32 €",
  "EuroTotaleTOT": "1.852.972,83 €",
  "TotaleDIF": "-9.397",
  "PercentualeDIF": "-14,91%",
  "Euro730DIF": "-199.817,10 €",
  "EuroPrecompDIF": "-33.014,19 €",
  "EuroIMUDIF": "2.617,59 €",
  "EuroTotaleDIF": "-226.518,47 €",
  "AppPossibiliOggi": "1.382",
  "App730Oggi": "760",
  "AppLiberiOggi": "265",
  "AppBlocchiOggi": "187",
  "AppPossibiliDomani": "1.409",
  "App730Domani": "685",
  "AppLiberiDomani": "308",
  "AppBlocchiDomani": "209",
  "DicStessoGiornoAP": "848",
  "ConStessoGiornoAP": "127",
  "TotStessoGiornoAP": "975",
  "DatiAggiornati": "Dati aggiornati al 09/07/2025 16:58:25"
}