{
  "GiornoAC": "mercoledì 24 giugno 2026",
  "DichiarantiAC": "369",
  "ConiugiAC": "55",
  "TotaleAC": "424",
  "Euro730AC": "12.105,53 €",
  "EuroPrecompAC": "880,33 €",
  "EuroIMUAC": "336,06 €",
  "EuroAltroAC": "174,58 €",
  "EuroTotaleAC": "13.496,50 €",
  "GiornoAP": "Differenza con mercoledì 25 giugno 2025",
  "DichiarantiAP": "-372",
  "ConiugiAP": "-77",
  "TotaleAP": "-449",
  "Euro730AP": "-14.907,62 €",
  "EuroPrecompAP": "-2.188,29 €",
  "EuroIMUAP": "-245,85 €",
  "EuroAltroAP": "43,41 €",
  "EuroTotaleAP": "-17.298,35 €",
  "DichiarantiTOT": "38.374",
  "ConiugiTOT": "7.315",
  "TotaleTOT": "45.689",
  "Euro730TOT": "1.487.014,04 €",
  "EuroPrecompTOT": "90.530,75 €",
  "EuroIMUTOT": "75.149,50 €",
  "EuroAltroTOT": "7.421,58 €",
  "EuroTotaleTOT": "1.660.115,87 €",
  "TotaleDIF": "-17.865",
  "PercentualeDIF": "-28,11%",
  "Euro730DIF": "-498.515,92 €",
  "EuroPrecompDIF": "-58.854,52 €",
  "EuroIMUDIF": "-667,95 €",
  "EuroAltroDIF": "-4.400,14 €",
  "EuroTotaleDIF": "-562.438,53 €",
  "AppPossibiliOggi": "1.135",
  "App730Oggi": "909",
  "AppLiberiOggi": "87",
  "AppBlocchiOggi": "53",
  "AppPossibiliDomani": "1.112",
  "App730Domani": "892",
  "AppLiberiDomani": "95",
  "AppBlocchiDomani": "21",
  "DicStessoGiornoAP": "-237",
  "ConStessoGiornoAP": "-43",
  "TotStessoGiornoAP": "-280",
  "DatiAggiornati": "Dati aggiornati al 24/06/2026 13:59:22"
}