{
  "GiornoAC": "giovedì 5 giugno 2025",
  "DichiarantiAC": "506",
  "ConiugiAC": "111",
  "TotaleAC": "617",
  "Euro730AC": "16.562,43 €",
  "EuroPrecompAC": "1.277,03 €",
  "EuroIMUAC": "1.137,58 €",
  "EuroTotaleAC": "19.074,60 €",
  "GiornoAP": "Differenza con giovedì 6 giugno 2024",
  "DichiarantiAP": "-264",
  "ConiugiAP": "-59",
  "TotaleAP": "-323",
  "Euro730AP": "-9.688,22 €",
  "EuroPrecompAP": "-1.116,24 €",
  "EuroIMUAP": "-897,40 €",
  "EuroTotaleAP": "-11.616,60 €",
  "DichiarantiTOT": "27.237",
  "ConiugiTOT": "5.121",
  "TotaleTOT": "32.358",
  "Euro730TOT": "1.006.912,02 €",
  "EuroPrecompTOT": "52.083,32 €",
  "EuroIMUTOT": "51.012,99 €",
  "EuroTotaleTOT": "1.113.920,49 €",
  "TotaleDIF": "-30.677",
  "PercentualeDIF": "-48,67%",
  "Euro730DIF": "-857.268,89 €",
  "EuroPrecompDIF": "-90.018,59 €",
  "EuroIMUDIF": "-19.106,74 €",
  "EuroTotaleDIF": "-965.570,81 €",
  "AppPossibiliOggi": "1.409",
  "App730Oggi": "962",
  "AppLiberiOggi": "70",
  "AppBlocchiOggi": "122",
  "AppPossibiliDomani": "1.350",
  "App730Domani": "1.052",
  "AppLiberiDomani": "30",
  "AppBlocchiDomani": "147",
  "DicStessoGiornoAP": "42",
  "ConStessoGiornoAP": "-71",
  "TotStessoGiornoAP": "-29",
  "DatiAggiornati": "Dati aggiornati al 05/06/2025 16:01:09"
}