{
  "GiornoAC": "mercoledì 18 giugno 2025",
  "DichiarantiAC": "167",
  "ConiugiAC": "35",
  "TotaleAC": "202",
  "Euro730AC": "5.001,93 €",
  "EuroPrecompAC": "546,72 €",
  "EuroIMUAC": "103,27 €",
  "EuroTotaleAC": "5.651,92 €",
  "GiornoAP": "Differenza con mercoledì 19 giugno 2024",
  "DichiarantiAP": "-570",
  "ConiugiAP": "-100",
  "TotaleAP": "-670",
  "Euro730AP": "-21.793,02 €",
  "EuroPrecompAP": "-1.239,97 €",
  "EuroIMUAP": "-650,73 €",
  "EuroTotaleAP": "-23.708,32 €",
  "DichiarantiTOT": "34.030",
  "ConiugiTOT": "6.529",
  "TotaleTOT": "40.559",
  "Euro730TOT": "1.252.001,42 €",
  "EuroPrecompTOT": "71.508,47 €",
  "EuroIMUTOT": "65.203,52 €",
  "EuroTotaleTOT": "1.393.356,88 €",
  "TotaleDIF": "-22.476",
  "PercentualeDIF": "-35,66%",
  "Euro730DIF": "-612.179,49 €",
  "EuroPrecompDIF": "-70.593,44 €",
  "EuroIMUDIF": "-4.916,21 €",
  "EuroTotaleDIF": "-686.134,42 €",
  "AppPossibiliOggi": "1.382",
  "App730Oggi": "983",
  "AppLiberiOggi": "88",
  "AppBlocchiOggi": "123",
  "AppPossibiliDomani": "1.409",
  "App730Domani": "974",
  "AppLiberiDomani": "71",
  "AppBlocchiDomani": "106",
  "DicStessoGiornoAP": "144",
  "ConStessoGiornoAP": "32",
  "TotStessoGiornoAP": "176",
  "DatiAggiornati": "Dati aggiornati al 18/06/2025 10:41:50"
}