{
  "GiornoAC": "lunedì 14 luglio 2025",
  "DichiarantiAC": "452",
  "ConiugiAC": "63",
  "TotaleAC": "515",
  "Euro730AC": "16.607,56 €",
  "EuroPrecompAC": "2.648,03 €",
  "EuroIMUAC": "127,86 €",
  "EuroTotaleAC": "19.562,18 €",
  "GiornoAP": "Differenza con lunedì 15 luglio 2024",
  "DichiarantiAP": "-22",
  "ConiugiAP": "-16",
  "TotaleAP": "-38",
  "Euro730AP": "-659,09 €",
  "EuroPrecompAP": "1.099,06 €",
  "EuroIMUAP": "-60,64 €",
  "EuroTotaleAP": "533,46 €",
  "DichiarantiTOT": "46.921",
  "ConiugiTOT": "8.751",
  "TotaleTOT": "55.672",
  "Euro730TOT": "1.730.595,81 €",
  "EuroPrecompTOT": "116.536,32 €",
  "EuroIMUTOT": "73.399,56 €",
  "EuroTotaleTOT": "1.928.419,15 €",
  "TotaleDIF": "-7.363",
  "PercentualeDIF": "-11,68%",
  "Euro730DIF": "-133.585,10 €",
  "EuroPrecompDIF": "-25.565,59 €",
  "EuroIMUDIF": "3.279,83 €",
  "EuroTotaleDIF": "-151.072,15 €",
  "AppPossibiliOggi": "1.386",
  "App730Oggi": "667",
  "AppLiberiOggi": "283",
  "AppBlocchiOggi": "318",
  "AppPossibiliDomani": "1.377",
  "App730Domani": "640",
  "AppLiberiDomani": "347",
  "AppBlocchiDomani": "138",
  "DicStessoGiornoAP": "1.141",
  "ConStessoGiornoAP": "140",
  "TotStessoGiornoAP": "1.281",
  "DatiAggiornati": "Dati aggiornati al 14/07/2025 17:48:50"
}