{
  "GiornoAC": "martedì 14 aprile 2026",
  "DichiarantiAC": "395",
  "ConiugiAC": "57",
  "TotaleAC": "452",
  "Euro730AC": "13.058,92 €",
  "EuroPrecompAC": "376,22 €",
  "EuroIMUAC": "368,84 €",
  "EuroAltroAC": "41,80 €",
  "EuroTotaleAC": "13.845,78 €",
  "GiornoAP": "Differenza con martedì 15 aprile 2025",
  "DichiarantiAP": "-145",
  "ConiugiAP": "-39",
  "TotaleAP": "-184",
  "Euro730AP": "-6.874,24 €",
  "EuroPrecompAP": "-336,86 €",
  "EuroIMUAP": "-686,80 €",
  "EuroAltroAP": "-85,27 €",
  "EuroTotaleAP": "-7.983,17 €",
  "DichiarantiTOT": "1.803",
  "ConiugiTOT": "293",
  "TotaleTOT": "2.096",
  "Euro730TOT": "65.236,91 €",
  "EuroPrecompTOT": "1.956,56 €",
  "EuroIMUTOT": "3.106,45 €",
  "EuroAltroTOT": "338,51 €",
  "EuroTotaleTOT": "70.638,43 €",
  "TotaleDIF": "-61.458",
  "PercentualeDIF": "-96,70%",
  "Euro730DIF": "-1.920.293,05 €",
  "EuroPrecompDIF": "-147.428,71 €",
  "EuroIMUDIF": "-72.711,00 €",
  "EuroAltroDIF": "-11.483,21 €",
  "EuroTotaleDIF": "-2.151.915,97 €",
  "AppPossibiliOggi": "1.133",
  "App730Oggi": "584",
  "AppLiberiOggi": "99",
  "AppBlocchiOggi": "295",
  "AppPossibiliDomani": "1.128",
  "App730Domani": "989",
  "AppLiberiDomani": "16",
  "AppBlocchiDomani": "25",
  "DicStessoGiornoAP": "-950",
  "ConStessoGiornoAP": "-177",
  "TotStessoGiornoAP": "-1.127",
  "DatiAggiornati": "Dati aggiornati al 14/04/2026 17:29:36"
}