{
  "GiornoAC": "mercoledì 28 maggio 2025",
  "DichiarantiAC": "3",
  "ConiugiAC": "1",
  "TotaleAC": "4",
  "Euro730AC": "124,60 €",
  "EuroPrecompAC": "25,42 €",
  "EuroIMUAC": "0,00 €",
  "EuroTotaleAC": "162,32 €",
  "GiornoAP": "Differenza con mercoledì 29 maggio 2024",
  "DichiarantiAP": "-801",
  "ConiugiAP": "-158",
  "TotaleAP": "-959",
  "Euro730AP": "-29.659,04 €",
  "EuroPrecompAP": "-1.703,98 €",
  "EuroIMUAP": "-1.682,58 €",
  "EuroTotaleAP": "-33.033,30 €",
  "DichiarantiTOT": "23.188",
  "ConiugiTOT": "4.321",
  "TotaleTOT": "27.509",
  "Euro730TOT": "852.632,42 €",
  "EuroPrecompTOT": "42.022,21 €",
  "EuroIMUTOT": "41.603,99 €",
  "EuroTotaleTOT": "939.529,64 €",
  "TotaleDIF": "-35.526",
  "PercentualeDIF": "-56,36%",
  "Euro730DIF": "-1.011.548,49 €",
  "EuroPrecompDIF": "-100.079,70 €",
  "EuroIMUDIF": "-28.515,74 €",
  "EuroTotaleDIF": "-1.139.961,66 €",
  "AppPossibiliOggi": "1.169",
  "App730Oggi": "1.037",
  "AppLiberiOggi": "12",
  "AppBlocchiOggi": "16",
  "AppPossibiliDomani": "1.160",
  "App730Domani": "1.011",
  "AppLiberiDomani": "11",
  "AppBlocchiDomani": "46",
  "DicStessoGiornoAP": "730",
  "ConStessoGiornoAP": "98",
  "TotStessoGiornoAP": "828",
  "DatiAggiornati": "Dati aggiornati al 28/05/2025 08:54:59"
}