{
  "GiornoAC": "martedì 7 luglio 2026",
  "DichiarantiAC": "449",
  "ConiugiAC": "68",
  "TotaleAC": "517",
  "Euro730AC": "14.592,27 €",
  "EuroPrecompAC": "2.126,98 €",
  "EuroIMUAC": "426,22 €",
  "EuroAltroAC": "599,10 €",
  "EuroTotaleAC": "17.744,57 €",
  "GiornoAP": "Differenza con martedì 8 luglio 2025",
  "DichiarantiAP": "-202",
  "ConiugiAP": "-33",
  "TotaleAP": "-235",
  "Euro730AP": "-9.688,76 €",
  "EuroPrecompAP": "340,21 €",
  "EuroIMUAP": "72,14 €",
  "EuroAltroAP": "535,14 €",
  "EuroTotaleAP": "-8.741,27 €",
  "DichiarantiTOT": "44.446",
  "ConiugiTOT": "8.395",
  "TotaleTOT": "52.841",
  "Euro730TOT": "1.712.367,84 €",
  "EuroPrecompTOT": "112.891,65 €",
  "EuroIMUTOT": "79.358,41 €",
  "EuroAltroTOT": "10.374,90 €",
  "EuroTotaleTOT": "1.914.992,80 €",
  "TotaleDIF": "-10.713",
  "PercentualeDIF": "-16,86%",
  "Euro730DIF": "-273.162,12 €",
  "EuroPrecompDIF": "-36.493,62 €",
  "EuroIMUDIF": "3.540,96 €",
  "EuroAltroDIF": "-1.446,82 €",
  "EuroTotaleDIF": "-307.561,60 €",
  "AppPossibiliOggi": "1.119",
  "App730Oggi": "600",
  "AppLiberiOggi": "357",
  "AppBlocchiOggi": "37",
  "AppPossibiliDomani": "1.135",
  "App730Domani": "632",
  "AppLiberiDomani": "402",
  "AppBlocchiDomani": "21",
  "DicStessoGiornoAP": "-418",
  "ConStessoGiornoAP": "-50",
  "TotStessoGiornoAP": "-468",
  "DatiAggiornati": "Dati aggiornati al 07/07/2026 17:21:37"
}