{
  "GiornoAC": "mercoledì 3 giugno 2026",
  "DichiarantiAC": "385",
  "ConiugiAC": "69",
  "TotaleAC": "454",
  "Euro730AC": "14.151,42 €",
  "EuroPrecompAC": "816,40 €",
  "EuroIMUAC": "1.282,75 €",
  "EuroAltroAC": "41,80 €",
  "EuroTotaleAC": "16.292,37 €",
  "GiornoAP": "Differenza con mercoledì 4 giugno 2025",
  "DichiarantiAP": "-411",
  "ConiugiAP": "-84",
  "TotaleAP": "-495",
  "Euro730AP": "-15.545,43 €",
  "EuroPrecompAP": "-1.089,21 €",
  "EuroIMUAP": "-782,65 €",
  "EuroAltroAP": "-18,06 €",
  "EuroTotaleAP": "-17.435,35 €",
  "DichiarantiTOT": "26.676",
  "ConiugiTOT": "5.006",
  "TotaleTOT": "31.682",
  "Euro730TOT": "1.038.790,13 €",
  "EuroPrecompTOT": "55.127,69 €",
  "EuroIMUTOT": "51.899,97 €",
  "EuroAltroTOT": "3.567,35 €",
  "EuroTotaleTOT": "1.149.385,14 €",
  "TotaleDIF": "-31.872",
  "PercentualeDIF": "-50,15%",
  "Euro730DIF": "-946.739,83 €",
  "EuroPrecompDIF": "-94.257,58 €",
  "EuroIMUDIF": "-23.917,48 €",
  "EuroAltroDIF": "-8.254,37 €",
  "EuroTotaleDIF": "-1.073.169,26 €",
  "AppPossibiliOggi": "1.128",
  "App730Oggi": "989",
  "AppLiberiOggi": "46",
  "AppBlocchiOggi": "15",
  "AppPossibiliDomani": "1.112",
  "App730Domani": "978",
  "AppLiberiDomani": "12",
  "AppBlocchiDomani": "15",
  "DicStessoGiornoAP": "-400",
  "ConStessoGiornoAP": "-89",
  "TotStessoGiornoAP": "-489",
  "DatiAggiornati": "Dati aggiornati al 03/06/2026 14:39:27"
}