{
  "GiornoAC": "mercoledì 30 luglio 2025",
  "DichiarantiAC": "80",
  "ConiugiAC": "9",
  "TotaleAC": "89",
  "Euro730AC": "2.602,64 €",
  "EuroPrecompAC": "482,73 €",
  "EuroIMUAC": "134,42 €",
  "EuroTotaleAC": "3.232,09 €",
  "GiornoAP": "Differenza con mercoledì 31 luglio 2024",
  "DichiarantiAP": "-21",
  "ConiugiAP": "-4",
  "TotaleAP": "-25",
  "Euro730AP": "-686,09 €",
  "EuroPrecompAP": "-885,94 €",
  "EuroIMUAP": "82,79 €",
  "EuroTotaleAP": "-1.550,71 €",
  "DichiarantiTOT": "50.017",
  "ConiugiTOT": "9.173",
  "TotaleTOT": "59.190",
  "Euro730TOT": "1.841.036,35 €",
  "EuroPrecompTOT": "131.170,83 €",
  "EuroIMUTOT": "74.755,19 €",
  "EuroTotaleTOT": "2.055.782,01 €",
  "TotaleDIF": "-3.845",
  "PercentualeDIF": "-6,10%",
  "Euro730DIF": "-23.144,56 €",
  "EuroPrecompDIF": "-10.931,08 €",
  "EuroIMUDIF": "4.635,46 €",
  "EuroTotaleDIF": "-23.709,29 €",
  "AppPossibiliOggi": "381",
  "App730Oggi": "146",
  "AppLiberiOggi": "59",
  "AppBlocchiOggi": "74",
  "AppPossibiliDomani": "416",
  "App730Domani": "164",
  "AppLiberiDomani": "41",
  "AppBlocchiDomani": "91",
  "DicStessoGiornoAP": "142",
  "ConStessoGiornoAP": "-60",
  "TotStessoGiornoAP": "82",
  "DatiAggiornati": "Dati aggiornati al 30/07/2025 14:52:50"
}