{
  "GiornoAC": "giovedì 5 giugno 2025",
  "DichiarantiAC": "322",
  "ConiugiAC": "73",
  "TotaleAC": "395",
  "Euro730AC": "10.471,10 €",
  "EuroPrecompAC": "785,24 €",
  "EuroIMUAC": "786,80 €",
  "EuroTotaleAC": "12.087,41 €",
  "GiornoAP": "Differenza con giovedì 6 giugno 2024",
  "DichiarantiAP": "-448",
  "ConiugiAP": "-97",
  "TotaleAP": "-545",
  "Euro730AP": "-15.779,55 €",
  "EuroPrecompAP": "-1.608,03 €",
  "EuroIMUAP": "-1.248,18 €",
  "EuroTotaleAP": "-18.603,79 €",
  "DichiarantiTOT": "27.048",
  "ConiugiTOT": "5.081",
  "TotaleTOT": "32.129",
  "Euro730TOT": "1.000.820,69 €",
  "EuroPrecompTOT": "51.591,53 €",
  "EuroIMUTOT": "50.662,21 €",
  "EuroTotaleTOT": "1.106.933,30 €",
  "TotaleDIF": "-30.906",
  "PercentualeDIF": "-49,03%",
  "Euro730DIF": "-863.360,22 €",
  "EuroPrecompDIF": "-90.510,38 €",
  "EuroIMUDIF": "-19.457,52 €",
  "EuroTotaleDIF": "-972.558,00 €",
  "AppPossibiliOggi": "1.160",
  "App730Oggi": "973",
  "AppLiberiOggi": "34",
  "AppBlocchiOggi": "34",
  "AppPossibiliDomani": "1.153",
  "App730Domani": "1.051",
  "AppLiberiDomani": "20",
  "AppBlocchiDomani": "29",
  "DicStessoGiornoAP": "-147",
  "ConStessoGiornoAP": "-111",
  "TotStessoGiornoAP": "-258",
  "DatiAggiornati": "Dati aggiornati al 05/06/2025 12:36:07"
}