{
  "GiornoAC": "lunedì 14 luglio 2025",
  "DichiarantiAC": "340",
  "ConiugiAC": "38",
  "TotaleAC": "378",
  "Euro730AC": "11.164,63 €",
  "EuroPrecompAC": "2.371,81 €",
  "EuroIMUAC": "103,27 €",
  "EuroTotaleAC": "13.769,24 €",
  "GiornoAP": "Differenza con lunedì 15 luglio 2024",
  "DichiarantiAP": "-134",
  "ConiugiAP": "-41",
  "TotaleAP": "-175",
  "Euro730AP": "-6.102,02 €",
  "EuroPrecompAP": "822,84 €",
  "EuroIMUAP": "-85,23 €",
  "EuroTotaleAP": "-5.259,48 €",
  "DichiarantiTOT": "46.809",
  "ConiugiTOT": "8.726",
  "TotaleTOT": "55.535",
  "Euro730TOT": "1.725.152,88 €",
  "EuroPrecompTOT": "116.260,10 €",
  "EuroIMUTOT": "73.374,97 €",
  "EuroTotaleTOT": "1.922.626,21 €",
  "TotaleDIF": "-7.500",
  "PercentualeDIF": "-11,90%",
  "Euro730DIF": "-139.028,03 €",
  "EuroPrecompDIF": "-25.841,81 €",
  "EuroIMUDIF": "3.255,24 €",
  "EuroTotaleDIF": "-156.865,09 €",
  "AppPossibiliOggi": "1.386",
  "App730Oggi": "675",
  "AppLiberiOggi": "273",
  "AppBlocchiOggi": "320",
  "AppPossibiliDomani": "1.377",
  "App730Domani": "639",
  "AppLiberiDomani": "352",
  "AppBlocchiDomani": "136",
  "DicStessoGiornoAP": "1.029",
  "ConStessoGiornoAP": "115",
  "TotStessoGiornoAP": "1.144",
  "DatiAggiornati": "Dati aggiornati al 14/07/2025 15:48:49"
}