{
  "GiornoAC": "mercoledì 27 maggio 2026",
  "DichiarantiAC": "329",
  "ConiugiAC": "80",
  "TotaleAC": "409",
  "Euro730AC": "11.285,18 €",
  "EuroPrecompAC": "897,53 €",
  "EuroIMUAC": "971,29 €",
  "EuroAltroAC": "29,50 €",
  "EuroTotaleAC": "13.183,50 €",
  "GiornoAP": "Differenza con mercoledì 28 maggio 2025",
  "DichiarantiAP": "-465",
  "ConiugiAP": "-86",
  "TotaleAP": "-551",
  "Euro730AP": "-18.739,58 €",
  "EuroPrecompAP": "-1.078,62 €",
  "EuroIMUAP": "-903,95 €",
  "EuroAltroAP": "-57,42 €",
  "EuroTotaleAP": "-20.779,57 €",
  "DichiarantiTOT": "23.587",
  "ConiugiTOT": "4.429",
  "TotaleTOT": "28.016",
  "Euro730TOT": "920.882,79 €",
  "EuroPrecompTOT": "45.903,27 €",
  "EuroIMUTOT": "45.568,20 €",
  "EuroAltroTOT": "3.302,57 €",
  "EuroTotaleTOT": "1.015.656,83 €",
  "TotaleDIF": "-35.538",
  "PercentualeDIF": "-55,92%",
  "Euro730DIF": "-1.064.647,17 €",
  "EuroPrecompDIF": "-103.482,00 €",
  "EuroIMUDIF": "-30.249,25 €",
  "EuroAltroDIF": "-8.519,15 €",
  "EuroTotaleDIF": "-1.206.897,57 €",
  "AppPossibiliOggi": "1.128",
  "App730Oggi": "1.017",
  "AppLiberiOggi": "31",
  "AppBlocchiOggi": "6",
  "AppPossibiliDomani": "1.112",
  "App730Domani": "988",
  "AppLiberiDomani": "9",
  "AppBlocchiDomani": "29",
  "DicStessoGiornoAP": "-586",
  "ConStessoGiornoAP": "-99",
  "TotStessoGiornoAP": "-685",
  "DatiAggiornati": "Dati aggiornati al 27/05/2026 12:43:14"
}